minesight/__init__.py
minesight/lookup.py
minesight/main.py
minesight/mojang.py
minesight/sites.json
minesight/utils.py
MineSight-1.0.13.dist-info/METADATA
MineSight-1.0.13.dist-info/WHEEL
MineSight-1.0.13.dist-info/entry_points.txt
MineSight-1.0.13.dist-info/top_level.txt
MineSight-1.0.13.dist-info/RECORD
